{
  "priorities": {
    "priority1": 23,
    "priority2": 43,
    "priority3": 432,
    "priority4": 41
  },
  "regions": {
    "Northeast": [
      {
        "en": "Northeast. Lorem ipsum. sakdsajdsal.",
        "fr": "Northeast French. djsadkjaldj. sajdaskldlkas"
      }
    ],
    "Southeast": [
      {
        "en": "dffdsd. dsfsdf.dsfsdfsd",
        "fr": "dsdsdadas. sadsad. dsadasd"
      },
      {
        "en": "dsfsdfdsfds. fdfdsffd. dsfdsfsd.",
        "fr": "dfdsfdfsf. fdsfsd. fds"
      }
    ],
    "West": [
      {
        "en": "sadsadasd. sasdsadsa. dsadasdsa",
        "fr": ""
      }
    ],
    "Codiac": [
      {
        "en": "dsadsadsadsad. dsadsasd. ssaddsds",
        "fr": ""
      }
    ]
  }
}
